bits/__init__.py
bits/sendgrid/__init__.py
bits_sendgrid-1.0.4.dist-info/METADATA
bits_sendgrid-1.0.4.dist-info/WHEEL
bits_sendgrid-1.0.4.dist-info/top_level.txt
bits_sendgrid-1.0.4.dist-info/RECORD
